fasteasySD/LCM_LoRa_Sampler.py
fasteasySD/LCM_LoRa_img2img_Sampler.py
fasteasySD/LCM_Sampler.py
fasteasySD/LCM_img2img_Sampler.py
fasteasySD/LCM_onnx_Sampler.py
fasteasySD/LCM_onnx_img2img_Sampler.py
fasteasySD/__init__.py
fasteasySD/main_class.py
fasteasySD-0.3.0.dist-info/LICENSE
fasteasySD-0.3.0.dist-info/METADATA
fasteasySD-0.3.0.dist-info/WHEEL
fasteasySD-0.3.0.dist-info/top_level.txt
fasteasySD-0.3.0.dist-info/RECORD
