Metadata-Version: 2.1
Name: fasteasySD
Version: 0.3.0
Summary: Simplified library for comfyUI-lcm extensions. support txt2img or img2img
Author-email: WaGaNaWa <m4a1carbin4@gmail.com>
Project-URL: Homepage, https://github.com/m4a1carbin4/fasteasysd
Project-URL: Bug Tracker, https://github.com/m4a1carbin4/fasteasysd/issues
Classifier: Programming Language :: Python :: 3
Classifier: Operating System :: OS Independent
Requires-Python: >=3.10
License-File: LICENSE
Requires-Dist: diffusers >=0.21.4
Requires-Dist: numpy >=1.26.1
Requires-Dist: torch >=2.1.0
Requires-Dist: torchvision >=0.16.0
Requires-Dist: transformers >=4.34.1
Requires-Dist: accelerate >=0.24.0
Requires-Dist: omegaconf >=2.3.0
